{
    "room":                     "Nightcore 331",
    "author":                   "donvoo & greySynapse",
    "css":                      "https://rawgit.com/donvoo/nc/master/NC.css",
    "rules": {
        "allowAutorespond":     true,
        "allowAutowoot":        true,
        "allowAutojoin":        true,
        "allowAutograb":        true,
        "allowSmartVote":       true,
        "allowEmotes":          true,
        "allowShowingMehs":     true,
        "forceSmartVote":       false
    },
    "ccc": {
        "admin":                "#1eb6e7",
        "ambassador":           "#1bbc5f",
        "host":                 "#923892",
        "cohost":               "#87449c",
        "manager":              "#7854a9",
        "bouncer":              "#626cbc",
        "rdj":                  "#547bc9",
        "subscriber":           null,
        "friend":               null,
        "user":                 null
    },
    "images": {
        "background":           "http://i.imgur.com/wH6pNHm.png",
        "playback":             "http://i.imgur.com/IGumCv2.png",
        "admin":                "http://i.imgur.com/jAhVtVF.png",
        "ambassador":           "http://i.imgur.com/HWucg1I.png",
        "host":                 "http://i.imgur.com/2HztU2h.png",
        "cohost":               "http://i.imgur.com/2HztU2h.png",
        "manager":              "http://i.imgur.com/bebMb8k.png",
        "bouncer":              "http://i.imgur.com/jA7CGAX.png",
        "rdj":                  "http://i.imgur.com/EBEFOAY.png",
        "subscriber":           null
    },
    "autocomplete": [],
    "emotes": {
        "firelenny":            "http://i.imgur.com/jleilmo.gif",
        "gs_heart":             "http://i.imgur.com/JMcr6ag.png"
    }
}
